django_bootstrap3_daterangepicker/__init__.py
django_bootstrap3_daterangepicker/fields.py
django_bootstrap3_daterangepicker/widgets.py
django_bootstrap3_daterangepicker/static/daterangepicker/daterangepicker.css
django_bootstrap3_daterangepicker/static/daterangepicker/daterangepicker.js
django_bootstrap3_daterangepicker/static/momentjs/moment.js
django_bootstrap3_daterangepicker/static/momentjs/moment.min.js
django_bootstrap3_daterangepicker-1.0.0b4.dist-info/DESCRIPTION.rst
django_bootstrap3_daterangepicker-1.0.0b4.dist-info/METADATA
django_bootstrap3_daterangepicker-1.0.0b4.dist-info/RECORD
django_bootstrap3_daterangepicker-1.0.0b4.dist-info/WHEEL
django_bootstrap3_daterangepicker-1.0.0b4.dist-info/metadata.json
django_bootstrap3_daterangepicker-1.0.0b4.dist-info/top_level.txt
