Metadata-Version: 2.0
Name: django-bootstrap3-daterangepicker
Version: 1.0.0b4
Summary: Django date range form field
Home-page: https://github.com/YuriMalinov/django-bootstrap3-daterangepicker/
Author: Yuri Malinov
Author-email: yurik.m@gmail.com
License: MIT
Requires-Dist: django
